<?xml version="1.0" encoding="UTF-8"?>
<metadata xml:lang="en"><Esri><CreaDate>20161207</CreaDate><CreaTime>18102100</CreaTime><ArcGISFormat>1.0</ArcGISFormat><SyncOnce>TRUE</SyncOnce><DataProperties><itemProps><itemLocation><linkage Sync="TRUE">file://\\MONR-320-03\C$\Users\cpetroff\Remote-Sensing-Final\NLCD_Raster\finalnlcd</linkage><protocol Sync="TRUE">Local Area Network</protocol></itemLocation></itemProps><copyHistory><copy source="E:\Remote Sensing\Class Project\finalnlcd" dest="\\MONR-320-03\C$\Users\cpetroff\Remote-Sensing-Final\NLCD_Raster\finalnlcd" date="20161207" time="18102100"></copy></copyHistory></DataProperties></Esri></metadata>
